[
  {
    "id": "match_pl_001_2026_man_utd_city",
    "teamA": {
      "name": "Rennes",
      "icon": "https://storage.livescore.com/images/team/medium/badge/man-utd.png"
    },
    "teamB": {
      "name": "PSG",
      "icon": "https://storage.livescore.com/images/team/medium/badge/man-city.png"
    },
    "leagueName": "France Ligue 1",
    "prediction": "Away Win",
    "date": "2026-02-13"
  },
  {
    "id": "match_pl_002_2026_chelsea_brentford",
    "teamA": {
      "name": "Monaco",
      "icon": "https://storage.livescore.com/images/team/medium/badge/chelsea.png"
    },
    "teamB": {
      "name": "Nantes",
      "icon": "https://storage.livescore.com/images/team/medium/badge/brentford.png"
    },
    "leagueName": "France Ligue 1",
    "prediction": "Home Win",
    "date": "2026-02-13"
  },
  {
    "id": "match_pl_003_2026_leeds_fulham",
    "teamA": {
      "name": "Volendam",
      "icon": "https://storage.livescore.com/images/team/medium/badge/leeds.png"
    },
    "teamB": {
      "name": "PSV Eindhoven",
      "icon": "https://storage.livescore.com/images/team/medium/badge/fulham.png"
    },
    "leagueName": "Netherlands Eredivisie",
    "prediction": "Away Win",
    "date": "2026-02-13"
  },
  {
    "id": "match_pl_004_2026_liverpool_burnley",
    "teamA": {
      "name": "Santa Clara",
      "icon": "https://storage.livescore.com/images/team/medium/badge/liverpool.png"
    },
    "teamB": {
      "name": "SL Benfica",
      "icon": "https://storage.livescore.com/images/team/medium/badge/burnley.png"
    },
    "leagueName": "Portugal Liga Portugal",
    "prediction": "Away Win",
    "date": "2026-02-13"
  },
  {
    "id": "match_pl_005_2026_sunderland_palace",
    "teamA": {
      "name": "Randers FC",
      "icon": "https://storage.livescore.com/images/team/medium/badge/sunderland.png"
    },
    "teamB": {
      "name": "Vejle BK",
      "icon": "https://storage.livescore.com/images/team/medium/badge/crystal-palace.png"
    },
    "leagueName": "Denmark Superliga",
    "prediction": "Home Win",
    "date": "2026-02-13"
  },
  {
    "id": "match_pl_006_2026_tottenham_west_ham",
    "teamA": {
      "name": "Tottenham Hotspur",
      "icon": "https://storage.livescore.com/images/team/medium/badge/tottenham.png"
    },
    "teamB": {
      "name": "West Ham United",
      "icon": "https://storage.livescore.com/images/team/medium/badge/west-ham.png"
    },
    "leagueName": "Premier League",
    "prediction": "Home Win",
    "date": "2026-01-17"
  },
  {
    "id": "match_pl_007_2026_forest_arsenal",
    "teamA": {
      "name": "Nottingham Forest",
      "icon": "https://storage.livescore.com/images/team/medium/badge/nottm-forest.png"
    },
    "teamB": {
      "name": "Arsenal",
      "icon": "https://storage.livescore.com/images/team/medium/badge/arsenal.png"
    },
    "leagueName": "Premier League",
    "prediction": "Away Win",
    "date": "2026-01-17"
  },
  {
    "id": "match_ll_001_2026_real_madrid_levante",
    "teamA": {
      "name": "Real Madrid",
      "icon": "https://storage.livescore.com/images/team/medium/badge/real-madrid.png"
    },
    "teamB": {
      "name": "Levante",
      "icon": "https://storage.livescore.com/images/team/medium/badge/levante.png"
    },
    "leagueName": "LaLiga",
    "prediction": "Home Win",
    "date": "2026-01-17"
  },
  {
    "id": "match_ll_002_2026_mallorca_athletic",
    "teamA": {
      "name": "Mallorca",
      "icon": "https://storage.livescore.com/images/team/medium/badge/mallorca.png"
    },
    "teamB": {
      "name": "Athletic Club",
      "icon": "https://storage.livescore.com/images/team/medium/badge/athletic-bilbao.png"
    },
    "leagueName": "LaLiga",
    "prediction": "Draw",
    "date": "2026-01-17"
  },
  {
    "id": "match_ll_003_2026_osasuna_oviedo",
    "teamA": {
      "name": "Osasuna",
      "icon": "https://storage.livescore.com/images/team/medium/badge/osasuna.png"
    },
    "teamB": {
      "name": "Real Oviedo",
      "icon": "https://storage.livescore.com/images/team/medium/badge/oviedo.png"
    },
    "leagueName": "LaLiga",
    "prediction": "Home Win",
    "date": "2026-01-17"
  },
  {
    "id": "match_ll_004_2026_betis_villarreal",
    "teamA": {
      "name": "Real Betis",
      "icon": "https://storage.livescore.com/images/team/medium/badge/real-betis.png"
    },
    "teamB": {
      "name": "Villarreal",
      "icon": "https://storage.livescore.com/images/team/medium/badge/villarreal.png"
    },
    "leagueName": "LaLiga",
    "prediction": "Over 2.5 Goals",
    "date": "2026-01-17"
  },
  {
    "id": "match_bund_001_2026_dortmund_st_pauli",
    "teamA": {
      "name": "Borussia Dortmund",
      "icon": "https://storage.livescore.com/images/team/medium/badge/borussia-dortmund.png"
    },
    "teamB": {
      "name": "St. Pauli",
      "icon": "https://storage.livescore.com/images/team/medium/badge/st-pauli.png"
    },
    "leagueName": "Bundesliga",
    "prediction": "Home Win",
    "date": "2026-01-17"
  },
  {
    "id": "match_bund_006_2026_leipzig_bayern",
    "teamA": {
      "name": "RB Leipzig",
      "icon": "https://storage.livescore.com/images/team/medium/badge/rb-leipzig.png"
    },
    "teamB": {
      "name": "Bayern Munich",
      "icon": "https://storage.livescore.com/images/team/medium/badge/bayern-munich.png"
    },
    "leagueName": "Bundesliga",
    "prediction": "Over 2.5 Goals (Classic high-scoring clash)",
    "date": "2026-01-17"
  }
]
